finetuning/__init__.py
finetuning-0.1.0.dist-info/METADATA
finetuning-0.1.0.dist-info/WHEEL
finetuning-0.1.0.dist-info/top_level.txt
finetuning-0.1.0.dist-info/RECORD
