Metadata-Version: 2.4
Name: finetuning
Version: 0.1.0
Summary: Modern fine-tuning library for LLMs with LoRA, QLoRA, and full fine-tuning support
Home-page: https://github.com/synth-ai/finetuning
Author: Synth AI
Author-email: Synth AI <team@synth.ai>
License: MIT
Keywords: machine-learning,deep-learning,transformers,fine-tuning,lora,llm
Requires-Python: >=3.8
Dynamic: author
Dynamic: home-page
Dynamic: requires-python
